streamlit_template/__init__.py
streamlit_template/__main__.py
streamlit_template/match_navbar.py
streamlit_template/frontend/package.json
streamlit_template/frontend/tsconfig.json
streamlit_template/frontend/build/asset-manifest.json
streamlit_template/frontend/build/bootstrap.min.css
streamlit_template/frontend/build/index.html
streamlit_template/frontend/build/static/js/main.4681a4cf.js
streamlit_template/frontend/build/static/js/main.4681a4cf.js.LICENSE.txt
streamlit_template/frontend/build/static/js/main.4681a4cf.js.map
streamlit_template/frontend/public/bootstrap.min.css
streamlit_template/frontend/public/index.html
streamlit_template/frontend/src/circle-to-polygon.tsx
streamlit_template/frontend/src/index.tsx
streamlit_template/frontend/src/react-app-env.d.ts
streamlit_template/templates/base.css
streamlit_template/templates/options.css
streamlit_template-0.0.5.dist-info/licenses/LICENSE
streamlit_template-0.0.5.dist-info/METADATA
streamlit_template-0.0.5.dist-info/WHEEL
streamlit_template-0.0.5.dist-info/entry_points.txt
streamlit_template-0.0.5.dist-info/top_level.txt
streamlit_template-0.0.5.dist-info/RECORD
