Metadata-Version: 2.4
Name: streamlit-template
Version: 0.0.5
Summary: A html component
Home-page: https://github.com/streamlit-community/streamlit-template
Author: Hans Then
Author-email: hans.then@gmail.com
License: MIT License
Project-URL: Source Code, https://github.com/streamlit-community/streamlit-template
Project-URL: Bug Tracker, https://github.com/streamlit-community/streamlit-template/issues
Project-URL: Release notes, https://github.com/streamlit-community/streamlit-template/releases
Classifier: Development Status :: 5 - Production/Stable
Classifier: Environment :: Console
Classifier: Environment :: Web Environment
Classifier: Intended Audience :: Developers
Classifier: Intended Audience :: Science/Research
Classifier: License :: OSI Approved :: MIT License
Classifier: Programming Language :: Python :: 3.9
Classifier: Programming Language :: Python :: 3.10
Classifier: Programming Language :: Python :: 3.11
Classifier: Programming Language :: Python :: 3.12
Classifier: Topic :: Database :: Front-Ends
Classifier: Topic :: Office/Business :: Financial :: Spreadsheet
Classifier: Topic :: Scientific/Engineering :: Information Analysis
Classifier: Topic :: Scientific/Engineering :: Visualization
Classifier: Topic :: Software Development :: Libraries :: Application Frameworks
Classifier: Topic :: Software Development :: Widget Sets
Requires-Python: >=3.9
License-File: LICENSE
Requires-Dist: streamlit>1.38.0
Dynamic: author
Dynamic: author-email
Dynamic: classifier
Dynamic: description
Dynamic: description-content-type
Dynamic: home-page
Dynamic: license
Dynamic: license-file
Dynamic: project-url
Dynamic: requires-dist
Dynamic: requires-python
Dynamic: summary
